LICENSE
MANIFEST.in
README.md
setup.cfg
setup.py
debug_permissions/__init__.py
debug_permissions/apps.py
debug_permissions/management/__init__.py
debug_permissions/management/commands/__init__.py
debug_permissions/management/commands/get_all_permissions.py
django_debug_permissions.egg-info/PKG-INFO
django_debug_permissions.egg-info/SOURCES.txt
django_debug_permissions.egg-info/dependency_links.txt
django_debug_permissions.egg-info/not-zip-safe
django_debug_permissions.egg-info/pbr.json
django_debug_permissions.egg-info/requires.txt
django_debug_permissions.egg-info/top_level.txt