Metadata-Version: 1.1
Name: django-debug-permissions
Version: 1.0.0
Summary: Get a list of all user permissions available in the Django system
Home-page: https://github.com/timonweb/django-debug-permissions
Author: Tim Kamanin
Author-email: tim@timonweb.com
License: BSD license
Keywords: django,debug,permissions,development,cli
Platform: UNKNOWN
Classifier: Development Status :: 4 - Beta
Classifier: Environment :: Web Environment
Classifier: Framework :: Django
Classifier: Intended Audience :: Developers
Classifier: License :: OSI Approved :: BSD License
Classifier: Natural Language :: English
Classifier: Programming Language :: Python :: 3
Classifier: Programming Language :: Python :: 3.3
Classifier: Programming Language :: Python :: 3.4
Classifier: Programming Language :: Python :: 3.5
Classifier: Programming Language :: Python :: 3.6
